[
    {
        "link": "./mclaren.html",
        "label": "McLaren",
        "backImg": "./images/team-logos/mclaren-logo.jpg"
    },
    {
        "link": "",
        "label": "RedBull",
        "backImg": "./images/team-logos/red-bull-logo.jpg"
    },
    {
        "link": "",
        "label": "VCARB",
        "backImg": "./images/team-logos/vcarb-logo.jpg"
    },
    {
        "link": "",
        "label": "Ferrari",
        "backImg": "./images/team-logos/ferrari-logo.jpg"
    },
    {
        "link": "",
        "label": "Mercedes",
        "backImg": "./images/team-logos/mercedes-logo.PNG"
    },
    {
        "link": "",
        "label": "Williams",
        "backImg": "./images/team-logos/williams-logo.png"
    },
    {
        "link": "",
        "label": "Aston Martin",
        "backImg": "./images/team-logos/aston-martin-logo.webp"
    },
    {
        "link": "",
        "label": "Alpine",
        "backImg": "./images/team-logos/alpine-logo.jpg"
    },
    {
        "link": "",
        "label": "Sauber",
        "backImg": "./images/team-logos/stake-kick-sauber-logo.jpg"
    },
    {
        "link": "",
        "label": "Haas",
        "backImg": "./images/team-logos/haas-logo.png"
    }
]
